lab_002_register/register.sv
module register
(
    input wire clk,
    input wire reset,   // active high
    input wire [6:0] addr,
    input wire [7:0] data_w,
    input wire en_write,
    output reg [7:0] data_r,
    input wire en_read,

    // reg addr : 0x00
    output reg [7:0] CONFIG_0,

    // reg addr : 0x01
    output reg [2:0] CONFIG_1,
    output reg EN_0,

    // reg addr : 0x02
    input wire [7:0] STATUS_0,

    // reg addr : 0x03
    output reg EN_1,
    input wire [2:0] STATUS_2,
    input wire STATUS_1
);
    // Write Register Address : 0x00
    reg [7:0] config_0_next;

    always @(*)
    begin
        if (en_write && (addr == 7'h00))
            config_0_next = data_w; 
        else
            config_0_next = CONFIG_0;
    end

    always @(posedge clk or posedge reset)
    begin
        if (reset)
            CONFIG_0 <= 8'b00;
        else
            CONFIG_0 <= config_0_next;
    end

    // Write Register Address : 0x01
    reg EN_0_next;
    reg [2:0] config_1_next;

    always @(*)
    begin
        if (en_write && (addr == 7'h01))
        begin
            config_1_next = data_w[2:0];
            EN_0_next = data_w[7];
        end else
        begin
            config_1_next = CONFIG_0;
            EN_0_next = EN_0;
        end
    end

    always @(posedge clk or posedge reset)
    begin
        if (reset)
        begin
            CONFIG_1 <= 3'b000;
            EN_0 <= 1'b0;
        end else
        begin
            CONFIG_1 <= config_0_next;
            EN_0 <= EN_0_next;
        end
    end

    // Write Register Address : 0x03
    reg EN_1_next;

    always @(*)
    begin
        if (en_write && (addr == 7'h02))
        begin
            EN_1_next = data_w[0];
        end else
        begin
            EN_1_next = EN_0;
        end
    end

    always @(posedge clk or posedge reset)
    begin
        if (reset)
        begin
            EN_1 <= 1'b0;
        end else
        begin
            EN_1 <= EN_0_next;
        end
    end

    // Read
    reg [7:0] data_r_next;

    always @(*)
    begin
        if (en_read)
            case (addr)
                7'h00 : data_r_next = CONFIG_0;
                7'h01 : data_r_next = {EN_0, {3{1'b0}}, CONFIG_1, 1'b1};
                7'h02 : data_r_next = STATUS_0;
                7'h03 : data_r_next = {STATUS_1, {2{1'b0}}, STATUS_2, 1'b0, EN_0};
                default : data_r_next = 8'h00;
            endcase
        else
            data_r_next = data_r;
    end

    always @(posedge clk or posedge reset)
    begin
        if (reset)
            data_r <= 8'h00;
        else
            data_r <= data_r_next;
    end

endmodule

lab_001_spi/spi.v
module spi
(
    input wire clk,
    input wire reset,   // active high
    input wire ssn,     // active low
    input wire sck,
    input wire sdi,
    output wire sdo,
    output reg [6:0] addr,
    output wire [7:0] data_w,
    output reg en_write,
    input wire [7:0] data_r,
    output reg en_read
);
    // *** Please modify the code only between start/stop comment blocks.

    //      ___                                                                                                    ___
    // SSn     |__________________________________________________________________________________________________|
    //             __    __    __    __    __    __    __    __    __    __    __    __    __    __    __    __   
    // SCK  ______^  |__^  |__^  |__^  |__^  |__^  |__^  |__^  |__^  |__^  |__^  |__^  |__^  |__^  |__^  |__^  |______           
    //             _  _________________________________________ _______________________________________________
    // SDI  ___| R/W |________________7-bit_address____________|_____________8-bit_data_to_write_______________|______
    //                                                          _______________________________________________
    // SDO  ___________________________________________________|_____________8-bit_data_to_read________________|______
    
    // ================================
    //    SPI mode 0 : Write Command
    // ================================
    //      ___                                                                                                    ___
    // SSn     |__________________________________________________________________________________________________|
    //             __    __    __    __    __    __    __    __    __    __    __    __    __    __    __    __   
    // SCK  ______^  |__^  |__^  |__^  |__^  |__^  |__^  |__^  |__^  |__^  |__^  |__^  |__^  |__^  |__^  |__^  |______           
    //
    // SDI  ______0__|  A6 |  A5 |  A4 |  A3 |  A2 |  A1 |  A0 |  W7 |  W6 |  W5 |  W4 |  W3 |  W2 |  W1 |  W0 |______
    //
    // SDO  __________________________________________________________________________________________________________
    
    // ================================
    //    SPI mode 0 : Read Command
    // ================================
    //      ___                                                                                                    ___
    // SSn     |__________________________________________________________________________________________________|
    //             __    __    __    __    __    __    __    __    __    __    __    __    __    __    __    __   
    // SCK  ______^  |__^  |__^  |__^  |__^  |__^  |__^  |__^  |__^  |__^  |__^  |__^  |__^  |__^  |__^  |__^  |______           
    //          _____   
    // SDI  ___|  1  |  A6 |  A5 |  A4 |  A3 |  A2 |  A1 |  A0 |______________________________________________________
    //
    // SDO  ___________________________________________________|  R7 |  R6 |  R5 |  R4 |  R3 |  R2 |  R1 |  R0 |______
    //   
    
    // ================================================
    // detect rising edge and falling edge of sck
    // ================================================
    reg sck_prev, sck_prev_d;
    wire sck_posedge;
    wire sck_negedge;

    always @(*)
    begin
        if (ssn)
            sck_prev_d = 1'b0;
        else
            sck_prev_d = sck;
    end

    always @(posedge clk, posedge reset)
    begin
        if (reset)
            sck_prev <= 1'b0;
        else
            sck_prev <= sck_prev_d;
    end

    // start to fix combination logic : sck_posedge
    assign sck_posedge = 1'b0;
    // end : sck_posedge

    // start to fix combination logic : sck_negedge
    assign sck_negedge = 1'b0;
    // end : sck_negedge

    // ================================================
    // bit counter
    // ================================================
    reg [4:0] counter, counter_next;

    always @(*)
    begin
        // start to fix combination logic : counter_next
        counter_next = counter;
        // end : counter_next
    end

    always @(posedge clk or posedge reset)
    begin
        if (reset)
            counter <= 5'h00;
        else
            counter <= counter_next;
    end

    // ================================================
    // Read/Write bit
    // ================================================
    reg rw_bit, rw_bit_next; // rw_bit = 1 -> read, rw_bit = 0 -> write
    
    always @(*)
    begin
        // start to fix combination logic : rw_bit_next
        rw_bit_next = rw_bit;
        // end : rw_bit_next
    end

    always @(posedge clk or posedge reset)
    begin
        if (reset)
            rw_bit <= 1'b0;
        else
            rw_bit <= rw_bit_next;
    end

    // ================================================
    // en_write
    // ================================================
    reg en_write_next;

    always @(*)
    begin
        // start to fix combination logic : en_write_next
        en_write_next = en_write;
        // end : en_write_next
    end

    always @(posedge clk or posedge reset)
    begin
        if (reset)
            en_write <= 1'b0;
        else
            en_write <= en_write_next;
    end

    // ================================================
    // en_read
    // ================================================
    reg en_read_next;

    always @(*)
    begin
        // start to fix combination logic : en_read_next
        en_read_next = en_read;
        // end : en_read_next
    end

    always @(posedge clk or posedge reset)
    begin
        if (reset)
            en_read <= 1'b0;
        else
            en_read <= en_read_next;
    end

    // ================================================
    // shift_in from sdi
    // ================================================
    reg [15:0] shift_in, shift_in_next;

    always @(*)
    begin
        // start to fix combination logic : shift_in_next
        shift_in_next = shift_in;
        // end : shift_in_next
    end

    always @(posedge clk or posedge reset)
    begin
        if (reset)
            shift_in <= 16'h0000;
        else
            shift_in <= shift_in_next;
    end

    // ================================================
    // address
    // ================================================
    reg [6:0] addr_next;

    always @(*)
    begin
        // start to fix combination logic : addr_next
        addr_next = addr;
        // end : addr_next
    end

    always @(posedge clk or posedge reset)
    begin
        if (reset)
            addr <= 7'h00;
        else
            addr <= addr_next;
    end

    // ================================================
    // data_w
    // ================================================
    // start to fix combination logic : data_w
    assign data_w = shift_in[15:8];
    // end : data_w

    // ================================================
    // shift_out to sdo
    // ================================================
    reg [7:0] shift_out, shift_out_next;

    always @(*)
    begin
        // start to fix combination logic : shift_out_next
        shift_out_next = shift_out;
        // end : shift_out_next
    end

    always @(posedge clk or posedge reset)
    begin
        if (reset)
            shift_out <= 8'h00;
        else
            shift_out <= shift_out_next;
    end

    // start to fix combination logic : sdo
    assign sdo = shift_out[0];
    // end : sdo

endmodule

lab_002_register/tb.sv
`timescale 1ns/1ps

module tb
# (
    parameter CLK_FREQ_KHZ = 1000,
    parameter SCK_FREQ_KHZ = 100
)
();
    localparam CLK_PERIOD_NS = 1e9/(CLK_FREQ_KHZ * 1e3);
    localparam SCK_PERIOD_NS = 1e9/(SCK_FREQ_KHZ * 1e3);

    initial
        check_freq: assert (CLK_FREQ_KHZ > SCK_FREQ_KHZ)
        else
            $error("   *** Assertion failed!. CLK_FREQ_KHZ must be larger than SCK_FREQ_KHZ");

    logic clk;
    logic reset;            // active high
    logic ssn;              // active low
    logic sck;
    logic sdi;
    logic sdo;
    logic [6:0] addr;
    logic [7:0] data_w;
    logic en_write;
    logic [7:0] data_r;
    logic en_read;

    logic is_fail;
    logic [7:0] tb_write_data;
    logic [7:0] tb_read_data;
    logic [11:0] tb_status;

    // reg addr : 0x00
    logic [7:0] CONFIG_0;

    // reg addr : 0x01
    logic [2:0] CONFIG_1;
    logic EN_0;

    // reg addr : 0x02
    logic [7:0] STATUS_0;

    // reg addr : 0x03
    logic EN_1;
    logic [2:0] STATUS_2;
    logic STATUS_1;
    
    spi i_spi (.*);
    register i_register (.*);

    initial
    begin
        is_fail = 0;
        ssn = 1'b1;
        sck = 1'b0;
        sdi = 1'b0;
        Reset();

        STATUS_0 = 8'bXXXX_XXXX;
        STATUS_1 = 1'bX;
        STATUS_2 = 3'bXXX;

        $display("=============================");
        $display("   Register Reset Value");
        $display("=============================");
        $display("   CONFIG_0");
        test(CONFIG_0, 8'h00, 8);

        $display("\n   EN_0");
        test(EN_0, 1'b1, 1);

        $display("\n   CONFIG_1");
        test(CONFIG_1, 3'h5, 3);

        $display("\n   EN_1");
        test(EN_1, 1'b1, 1);

        $display("");
        $display("=============================");
        $display("   Read Reset Vaue via SPI");
        $display("=============================");
        spi_read(7'h00, tb_read_data);
        test(tb_read_data, 8'h00, 8);

        $display("");
        spi_read(7'h01, tb_read_data);
        test(tb_read_data, 8'h51, 8);

        $display("");
        spi_read(7'h02, tb_read_data);
        test(tb_read_data, 8'bXXXX_XXXX, 8);

        $display("");
        spi_read(7'h03, tb_read_data);
        test(tb_read_data, 8'b10XX_X00X, 8);

        $display("");
        Reset();
        for (int ii = 0; ii <= 8; ii = ii + 1)
        begin
            if (ii == 8)
                tb_write_data = 8'b00;
            else
                tb_write_data = {8{1 << ii}};

            $display("=============================");
            spi_write(8'h00, tb_write_data);
            $display("=============================");

            $display("   CONFIG_0");
            test(CONFIG_0, tb_write_data, 8);

            $display("\n   EN_0");
            test(EN_0, 1'b1, 1);

            $display("\n   CONFIG_1");
            test(CONFIG_1, 3'h5, 3);

            $display("\n   EN_1");
            test(EN_1, 1'b1, 1);
        end

        $display("");
        Reset();
        for (int ii = 0; ii <= 8; ii = ii + 1)
        begin
            if (ii == 8)
                tb_write_data = 8'b00;
            else
                tb_write_data = {8{1 << ii}};

            $display("=============================");
            spi_write(8'h01, tb_write_data);
            $display("=============================");
            $display("   CONFIG_0");
            test(CONFIG_0, 8'h00, 8);

            $display("\n   EN_0");
            test(EN_0, tb_write_data[0], 1);

            $display("\n   CONFIG_1");
            test(CONFIG_1, tb_write_data[6:4], 3);

            $display("\n   EN_1");
            test(EN_1, 1'b1, 1);
        end

        $display("");
        Reset();
        for (int ii = 0; ii <= 8; ii = ii + 1)
        begin
            if (ii == 8)
                tb_write_data = 8'b00;
            else
                tb_write_data = {8{1 << ii}};

            $display("=============================");
            spi_write(8'h02, tb_write_data);
            $display("=============================");

            $display("   CONFIG_0");
            test(CONFIG_0, 8'h00, 8);

            $display("\n   EN_0");
            test(EN_0, 1'b1, 1);

            $display("\n   CONFIG_1");
            test(CONFIG_1, 3'h5, 3);

            $display("\n   EN_1");
            test(EN_1, 1'b1, 1);
        end

        $display("");
        Reset();
        for (int ii = 0; ii <= 8; ii = ii + 1)
        begin
            if (ii == 8)
                tb_write_data = 8'b00;
            else
                tb_write_data = {8{1 << ii}};

            $display("=============================");
            spi_write(8'h03, tb_write_data);
            $display("=============================");

            $display("   CONFIG_0");
            test(CONFIG_0, 8'h00, 8);

            $display("\n   EN_0");
            test(EN_0, 1'b1, 1);

            $display("\n   CONFIG_1");
            test(CONFIG_1, 3'h5, 3);

            $display("\n   EN_1");
            test(EN_1, tb_write_data[7], 1);
        end

        $display("");
        Reset();
        for (int ii = 0; ii <= 12; ii = ii + 1)
        begin
            if (ii == 12)
                tb_status = 0;
            else
                tb_status = 1 << ii;

            STATUS_0 = tb_status[7:0];
            STATUS_1 = tb_status[8];
            STATUS_2 = tb_status[11:9];

            $display("=============================");
            $display("   Read Status for ii = %0d", ii);
            $display("=============================");
            spi_read(7'h00, tb_read_data);
            test(tb_read_data, 8'h00, 8);

            $display("");
            spi_read(7'h01, tb_read_data);
            test(tb_read_data, 8'h51, 8);

            $display("");
            spi_read(7'h02, tb_read_data);
            test(tb_read_data, tb_status[7:0], 8);

            $display("");
            spi_read(7'h03, tb_read_data);
            test(tb_read_data, {2'b10, tb_status[11:9], 2'b00, tb_status[8]}, 8);
        end

        #SCK_PERIOD_NS;
        $finish;
    end

    task spi_write;
        input [6:0] addr;
        input [7:0] data;
    begin
        logic [15:0] sdi_reg;
        real current_time;
        string str;
        
        current_time = $realtime / 1e6;
        sdi_reg = {1'b0, addr, data};
        ssn = 1'b1;
        sck = 1'b0;
        sdi = 1'b0;

        #SCK_PERIOD_NS;
        ssn = 1'b0;

        for (int ii = 0; ii < 16; ii = ii + 1)
        begin
            sdi = sdi_reg[15];
            #(SCK_PERIOD_NS/2);
            sck = 1'b1;
            #(SCK_PERIOD_NS/2);
            sck = 1'b0;
            sdi_reg = {sdi_reg[14:0], 1'b0};
        end

        $sformat(str, "%04b_%04b", data[7:4], data[3:0]);
        $display("   spi_write(h%02X, b%s)", addr, str.toupper());

        #(SCK_PERIOD_NS/2);
        ssn = 1'b1;
        #SCK_PERIOD_NS;
    end
    endtask

    task spi_read;
        input [6:0] addr;
        output [7:0] data;
    begin
        logic [15:0] sdi_reg;
        logic [7:0] read_data_temp;
        real current_time;
        string str;
        
        current_time = $realtime / 1e6;
        sdi_reg = {1'b1, addr, 8'h00};
        ssn = 1'b1;
        sck = 1'b0;
        sdi = 1'b0;

        #SCK_PERIOD_NS;
        ssn = 1'b0;

        for (int ii = 0; ii < 16; ii = ii + 1)
        begin
            sdi = sdi_reg[15];
            #(SCK_PERIOD_NS/2);
            sck = 1'b1;
            read_data_temp = {read_data_temp[6:0], sdo};
            #(SCK_PERIOD_NS/2);
            sck = 1'b0;
            sdi_reg = {sdi_reg[14:0], 1'b0};
        end

        data = read_data_temp;
        
        $sformat(str, "%04b_%04b", data[7:4], data[3:0]);
        $display("   spi_read(h%02X) -> b%s", addr, str.toupper());
        
        #(SCK_PERIOD_NS/2);
        ssn = 1'b1;
        #SCK_PERIOD_NS;
    end
    endtask

    task test;
        input logic [7:0] actual_data;
        input logic [7:0] expected_data;
        input integer bit_num;
    begin
        string str_t;
        string str_a;
        string str_e;

        str_a = "";
        str_e = "";
  
        for (int ii = 0; ii < bit_num; ii = ii + 1)
        begin
            if (ii == 4) begin
                str_a = {"_", str_a};
                str_e = {"_", str_e};
            end

            $sformat(str_t, "%01b", actual_data[ii]);
            str_a = {str_t, str_a};

            $sformat(str_t, "%01b", expected_data[ii]);
            str_e = {str_t, str_e};
        end

        if (actual_data === expected_data)
        begin
            $display("   %.3fus actual = b%s, expected = b%s : PASS", $realtime/1e6, str_a.toupper(), str_e.toupper());
        end else
        begin
            is_fail = 1;
            #SCK_PERIOD_NS;
            $display("   %.3fus actual = b%s, expected = b%s : FAIL", $realtime/1e6, str_a.toupper(), str_e.toupper());
            $finish;
        end
    end
    endtask

    task Reset();
        reset = 1'b1;
        @(posedge clk);
        @(negedge clk);
        reset = 1'b0;
    endtask

    initial
    begin
        clk = 0;
        forever begin
            #(CLK_PERIOD_NS/2);
            clk = ~clk;
        end
    end

    initial
    begin
        $dumpfile("sim.vcd");
        $dumpvars(0);
    end

    final
    begin
        if (is_fail)
        begin
$display("");
$display("=========================================="); $display("  $$$$$$$$\\  $$$$$$\\  $$$$$$\\ $$\\    "); $display("  $$  _____|$$  __$$\\ \\_$$  _|$$ |      ");
$display("  $$ |      $$ /  $$ |  $$ |  $$ |      "); $display("  $$$$$\\    $$$$$$$$ |  $$ |  $$ |      "); $display("  $$  __|   $$  __$$ |  $$ |  $$ |      ");
$display("  $$ |      $$ |  $$ |  $$ |  $$ |      "); $display("  $$ |      $$ |  $$ |$$$$$$\\ $$$$$$$$\\ "); $display("  \\__|      \\__|  \\__|\\______|\\________|");
$display("==========================================");
        end else
        begin
$display("=========================================="); $display("  $$$$$$$\\   $$$$$$\\   $$$$$$\\   $$$$$$\\  ");$display("  $$  __$$\\ $$  __$$\\ $$  __$$\\ $$  __$$\\ ");
$display("  $$ |  $$ |$$ /  $$ |$$ /  \\__|$$ /  \\__|");$display("  $$$$$$$  |$$$$$$$$ |\\$$$$$$\\  \\$$$$$$\\  "); $display("  $$  ____/ $$  __$$ | \\____$$\\  \\____$$\\ ");
$display("  $$ |      $$ |  $$ |$$\\   $$ |$$\\   $$ |"); $display("  $$ |      $$ |  $$ |\\$$$$$$  |\\$$$$$$  |");$display("  \\__|      \\__|  \\__| \\______/  \\______/ "); 
$display("==========================================");
        end
    end

endmodule

lab_002_register/sim_pass.vcd
$date
    Jul 24, 2026  19:10:20
$end
$version
    TOOL:	xmsim(64)	23.09-s013
$end
$timescale
    1 ps
$end

$scope module tb $end
$var parameter 32 !    CLK_FREQ_KHZ $end
$var parameter 32 "    SCK_FREQ_KHZ $end
$var real     64 #    CLK_PERIOD_NS $end
$var real     64 $    SCK_PERIOD_NS $end
$var reg       1 %    clk $end
$var reg       1 &    reset $end
$var reg       1 '    ssn $end
$var reg       1 (    sck $end
$var reg       1 )    sdi $end
$var reg       1 *    sdo $end
$var reg       7 +    addr [6:0] $end
$var reg       8 ,    data_w [7:0] $end
$var reg       1 -    en_write $end
$var reg       8 .    data_r [7:0] $end
$var reg       1 /    en_read $end
$var reg       1 0    is_fail $end
$var reg       8 1    tb_write_data [7:0] $end
$var reg       8 2    tb_read_data [7:0] $end
$var reg      12 3    tb_status [11:0] $end
$var reg       8 4    CONFIG_0 [7:0] $end
$var reg       3 5    CONFIG_1 [2:0] $end
$var reg       1 6    EN_0 $end
$var reg       8 7    STATUS_0 [7:0] $end
$var reg       1 8    EN_1 $end
$var reg       3 9    STATUS_2 [2:0] $end
$var reg       1 :    STATUS_1 $end

$scope module i_spi $end
$var wire      1 ;    clk  $end
$var wire      1 <    reset  $end
$var wire      1 =    ssn  $end
$var wire      1 >    sck  $end
$var wire      1 ?    sdi  $end
$var wire      1 @    sdo  $end
$var wire      1 A    addr [6] $end
$var wire      1 B    addr [5] $end
$var wire      1 C    addr [4] $end
$var wire      1 D    addr [3] $end
$var wire      1 E    addr [2] $end
$var wire      1 F    addr [1] $end
$var wire      1 G    addr [0] $end
$var wire      1 H    data_w [7] $end
$var wire      1 I    data_w [6] $end
$var wire      1 J    data_w [5] $end
$var wire      1 K    data_w [4] $end
$var wire      1 L    data_w [3] $end
$var wire      1 M    data_w [2] $end
$var wire      1 N    data_w [1] $end
$var wire      1 O    data_w [0] $end
$var wire      1 P    en_write  $end
$var wire      1 Q    data_r [7] $end
$var wire      1 R    data_r [6] $end
$var wire      1 S    data_r [5] $end
$var wire      1 T    data_r [4] $end
$var wire      1 U    data_r [3] $end
$var wire      1 V    data_r [2] $end
$var wire      1 W    data_r [1] $end
$var wire      1 X    data_r [0] $end
$var wire      1 Y    en_read  $end
$upscope $end


$scope module i_register $end
$var wire      1 Z    clk  $end
$var wire      1 [    reset  $end
$var wire      7 \    addr [6:0] $end
$var wire      8 ]    data_w [7:0] $end
$var wire      1 ^    en_write  $end
$var reg       8 _    data_r [7:0] $end
$var wire      1 `    en_read  $end
$var reg       8 a    CONFIG_0 [7:0] $end
$var reg       3 b    CONFIG_1 [2:0] $end
$var reg       1 c    EN_0 $end
$var wire      8 d    STATUS_0 [7:0] $end
$var reg       1 e    EN_1 $end
$var wire      3 f    STATUS_2 [2:0] $end
$var wire      1 g    STATUS_1  $end
$var reg       8 h    config_0_next [7:0] $end
$var reg       1 i    EN_0_next $end
$var reg       3 j    config_1_next [2:0] $end
$var reg       1 k    EN_1_next $end
$var reg       8 l    data_r_next [7:0] $end
$upscope $end


$scope task spi_write $end
$var reg       7 m    addr [6:0] $end
$var reg       8 n    data [7:0] $end

$scope begin unmblk1 $end
$var reg      16 o    sdi_reg [15:0] $end
$var real     64 p    current_time $end
$upscope $end

$upscope $end


$scope task spi_read $end
$var reg       7 q    addr [6:0] $end
$var reg       8 r    data [7:0] $end

$scope begin unmblk1 $end
$var reg      16 s    sdi_reg [15:0] $end
$var reg       8 t    read_data_temp [7:0] $end
$var real     64 u    current_time $end
$upscope $end

$upscope $end


$scope task test $end
$var reg       8 v    actual_data [7:0] $end
$var reg       8 w    expected_data [7:0] $end
$var integer  32 x    bit_num $end
$upscope $end

$upscope $end

$enddefinitions $end
$dumpvars
r10000 $
r1000 #
b1100100 "
b1111101000 !
0%
1&
1'
0(
0)
0*
b0 +
b0 ,
0-
b0 .
0/
00
bx 1
bx 2
bx 3
b0 4
b101 5
16
bx 7
18
bx 9
x:
0;
1<
1=
0>
0?
0@
0A
0B
0C
0D
0E
0F
0G
0H
0I
0J
0K
0L
0M
0N
0O
0P
0Q
0R
0S
0T
0U
0V
0W
0X
0Y
0Z
1[
b0 \
b0 ]
0^
b0 _
0`
b0 a
b101 b
1c
bx d
1e
bx f
xg
b0 h
1i
b101 j
1k
b0 l
bx m
bx n
bx o
r0 p
bx q
bx r
bx s
bx t
r0 u
bx v
bx w
bx x
$end
#500000
1%
1Z
1;
#1000000
0%
0&
b0 v
b0 w
b1000 x
b1 v
b1 w
b1 x
b101 v
b101 w
b11 x
b1 v
b1 w
b1 x
b0 q
r0.001 u
b1000000000000000 s
0[
0<
0Z
0;
#1500000
1%
1Z
1;
#2000000
0%
0Z
0;
#2500000
1%
1Z
1;
#3000000
0%
0Z
0;
#3500000
1%
1Z
1;
#4000000
0%
0Z
0;
#4500000
1%
1Z
1;
#5000000
0%
0Z
0;
#5500000
1%
1Z
1;
#6000000
0%
0Z
0;
#6500000
1%
1Z
1;
#7000000
0%
0Z
0;
#7500000
1%
1Z
1;
#8000000
0%
0Z
0;
#8500000
1%
1Z
1;
#9000000
0%
0Z
0;
#9500000
1%
1Z
1;
#10000000
0%
0Z
0;
#10500000
1%
1Z
1;
#11000000
0'
1)
0%
0Z
0;
1?
0=
#11500000
1%
1Z
1;
#12000000
0%
0Z
0;
#12500000
1%
1Z
1;
#13000000
0%
0Z
0;
#13500000
1%
1Z
1;
#14000000
0%
0Z
0;
#14500000
1%
1Z
1;
#15000000
0%
0Z
0;
#15500000
1%
1Z
1;
#16000000
1(
bx0 t
0%
0Z
0;
1>
#16500000
1%
1Z
1;
1O
b1 ,
b1 ]
#17000000
0%
0Z
0;
#17500000
1%
1Z
1;
#18000000
0%
0Z
0;
#18500000
1%
1Z
1;
#19000000
0%
0Z
0;
#19500000
1%
1Z
1;
#20000000
0%
0Z
0;
#20500000
1%
1Z
1;
#21000000
0(
b0 s
0)
0%
0Z
0;
0?
0>
#21500000
1%
1Z
1;
#22000000
0%
0Z
0;
#22500000
1%
1Z
1;
#23000000
0%
0Z
0;
#23500000
1%
1Z
1;
#24000000
0%
0Z
0;
#24500000
1%
1Z
1;
#25000000
0%
0Z
0;
#25500000
1%
1Z
1;
#26000000
1(
bx00 t
0%
0Z
0;
1>
#26500000
1%
1Z
1;
1N
0O
b10 ,
b10 ]
#27000000
0%
0Z
0;
#27500000
1%
1Z
1;
#28000000
0%
0Z
0;
#28500000
1%
1Z
1;
#29000000
0%
0Z
0;
#29500000
1%
1Z
1;
#30000000
0%
0Z
0;
#30500000
1%
1Z
1;
#31000000
0(
0%
0Z
0;
0>
#31500000
1%
1Z
1;
#32000000
0%
0Z
0;
#32500000
1%
1Z
1;
#33000000
0%
0Z
0;
#33500000
1%
1Z
1;
#34000000
0%
0Z
0;
#34500000
1%
1Z
1;
#35000000
0%
0Z
0;
#35500000
1%
1Z
1;
#36000000
1(
bx000 t
0%
0Z
0;
1>
#36500000
1%
1Z
1;
1M
0N
b100 ,
b100 ]
#37000000
0%
0Z
0;
#37500000
1%
1Z
1;
#38000000
0%
0Z
0;
#38500000
1%
1Z
1;
#39000000
0%
0Z
0;
#39500000
1%
1Z
1;
#40000000
0%
0Z
0;
#40500000
1%
1Z
1;
#41000000
0(
0%
0Z
0;
0>
#41500000
1%
1Z
1;
#42000000
0%
0Z
0;
#42500000
1%
1Z
1;
#43000000
0%
0Z
0;
#43500000
1%
1Z
1;
#44000000
0%
0Z
0;
#44500000
1%
1Z
1;
#45000000
0%
0Z
0;
#45500000
1%
1Z
1;
#46000000
1(
bx0000 t
0%
0Z
0;
1>
#46500000
1%
1Z
1;
1L
0M
b1000 ,
b1000 ]
#47000000
0%
0Z
0;
#47500000
1%
1Z
1;
#48000000
0%
0Z
0;
#48500000
1%
1Z
1;
#49000000
0%
0Z
0;
#49500000
1%
1Z
1;
#50000000
0%
0Z
0;
#50500000
1%
1Z
1;
#51000000
0(
0%
0Z
0;
0>
#51500000
1%
1Z
1;
#52000000
0%
0Z
0;
#52500000
1%
1Z
1;
#53000000
0%
0Z
0;
#53500000
1%
1Z
1;
#54000000
0%
0Z
0;
#54500000
1%
1Z
1;
#55000000
0%
0Z
0;
#55500000
1%
1Z
1;
#56000000
1(
bx00000 t
0%
0Z
0;
1>
#56500000
1%
1Z
1;
0L
1K
b10000 ,
b10000 ]
#57000000
0%
0Z
0;
#57500000
1%
1Z
1;
#58000000
0%
0Z
0;
#58500000
1%
1Z
1;
#59000000
0%
0Z
0;
#59500000
1%
1Z
1;
#60000000
0%
0Z
0;
#60500000
1%
1Z
1;
#61000000
0(
0%
0Z
0;
0>
#61500000
1%
1Z
1;
#62000000
0%
0Z
0;
#62500000
1%
1Z
1;
#63000000
0%
0Z
0;
#63500000
1%
1Z
1;
#64000000
0%
0Z
0;
#64500000
1%
1Z
1;
#65000000
0%
0Z
0;
#65500000
1%
1Z
1;
#66000000
1(
bx000000 t
0%
0Z
0;
1>
#66500000
1%
1Z
1;
1J
0K
b100000 ,
b100000 ]
#67000000
0%
0Z
0;
#67500000
1%
1Z
1;
#68000000
0%
0Z
0;
#68500000
1%
1Z
1;
#69000000
0%
0Z
0;
#69500000
1%
1Z
1;
#70000000
0%
0Z
0;
#70500000
1%
1Z
1;
#71000000
0(
0%
0Z
0;
0>
#71500000
1%
1Z
1;
#72000000
0%
0Z
0;
#72500000
1%
1Z
1;
#73000000
0%
0Z
0;
#73500000
1%
1Z
1;
#74000000
0%
0Z
0;
#74500000
1%
1Z
1;
#75000000
0%
0Z
0;
#75500000
1%
1Z
1;
#76000000
1(
bx0000000 t
0%
0Z
0;
1>
#76500000
1%
1Z
1;
1I
0J
b1000000 ,
b1000000 ]
#77000000
0%
0Z
0;
#77500000
1%
1Z
1;
#78000000
0%
0Z
0;
#78500000
1%
1Z
1;
#79000000
0%
0Z
0;
#79500000
1%
1Z
1;
#80000000
0%
0Z
0;
#80500000
1%
1Z
1;
#81000000
0(
0%
0Z
0;
0>
#81500000
1%
1Z
1;
#82000000
0%
0Z
0;
#82500000
1%
1Z
1;
#83000000
0%
0Z
0;
#83500000
1%
1Z
1;
#84000000
0%
0Z
0;
#84500000
1%
1Z
1;
#85000000
0%
0Z
0;
#85500000
1%
1Z
1;
#86000000
1(
b0 t
0%
0Z
0;
1>
#86500000
1%
1Z
1;
1Y
0I
1H
1/
b10000000 ,
b10000000 ]
1`
#87000000
0%
0Z
0;
#87500000
1%
1Z
1;
0Y
0/
0`
#88000000
0%
0Z
0;
#88500000
1%
1Z
1;
#89000000
0%
0Z
0;
#89500000
1%
1Z
1;
#90000000
0%
0Z
0;
#90500000
1%
1Z
1;
#91000000
0(
0%
0Z
0;
0>
#91500000
1%
1Z
1;
#92000000
0%
0Z
0;
#92500000
1%
1Z
1;
#93000000
0%
0Z
0;
#93500000
1%
1Z
1;
#94000000
0%
0Z
0;
#94500000
1%
1Z
1;
#95000000
0%
0Z
0;
#95500000
1%
1Z
1;
#96000000
1(
0%
0Z
0;
1>
#96500000
1%
1Z
1;
0H
b0 ,
b0 ]
#97000000
0%
0Z
0;
#97500000
1%
1Z
1;
#98000000
0%
0Z
0;
#98500000
1%
1Z
1;
#99000000
0%
0Z
0;
#99500000
1%
1Z
1;
#100000000
0%
0Z
0;
#100500000
1%
1Z
1;
#101000000
0(
0%
0Z
0;
0>
#101500000
1%
1Z
1;
#102000000
0%
0Z
0;
#102500000
1%
1Z
1;
#103000000
0%
0Z
0;
#103500000
1%
1Z
1;
#104000000
0%
0Z
0;
#104500000
1%
1Z
1;
#105000000
0%
0Z
0;
#105500000
1%
1Z
1;
#106000000
1(
0%
0Z
0;
1>
#106500000
1%
1Z
1;
#107000000
0%
0Z
0;
#107500000
1%
1Z
1;
#108000000
0%
0Z
0;
#108500000
1%
1Z
1;
#109000000
0%
0Z
0;
#109500000
1%
1Z
1;
#110000000
0%
0Z
0;
#110500000
1%
1Z
1;
#111000000
0(
0%
0Z
0;
0>
#111500000
1%
1Z
1;
#112000000
0%
0Z
0;
#112500000
1%
1Z
1;
#113000000
0%
0Z
0;
#113500000
1%
1Z
1;
#114000000
0%
0Z
0;
#114500000
1%
1Z
1;
#115000000
0%
0Z
0;
#115500000
1%
1Z
1;
#116000000
1(
0%
0Z
0;
1>
#116500000
1%
1Z
1;
#117000000
0%
0Z
0;
#117500000
1%
1Z
1;
#118000000
0%
0Z
0;
#118500000
1%
1Z
1;
#119000000
0%
0Z
0;
#119500000
1%
1Z
1;
#120000000
0%
0Z
0;
#120500000
1%
1Z
1;
#121000000
0(
0%
0Z
0;
0>
#121500000
1%
1Z
1;
#122000000
0%
0Z
0;
#122500000
1%
1Z
1;
#123000000
0%
0Z
0;
#123500000
1%
1Z
1;
#124000000
0%
0Z
0;
#124500000
1%
1Z
1;
#125000000
0%
0Z
0;
#125500000
1%
1Z
1;
#126000000
1(
0%
0Z
0;
1>
#126500000
1%
1Z
1;
#127000000
0%
0Z
0;
#127500000
1%
1Z
1;
#128000000
0%
0Z
0;
#128500000
1%
1Z
1;
#129000000
0%
0Z
0;
#129500000
1%
1Z
1;
#130000000
0%
0Z
0;
#130500000
1%
1Z
1;
